MANIFEST.in
setup.cfg
setup.py
Notario.minion.egg-info/PKG-INFO
Notario.minion.egg-info/SOURCES.txt
Notario.minion.egg-info/dependency_links.txt
Notario.minion.egg-info/entry_points.txt
Notario.minion.egg-info/requires.txt
Notario.minion.egg-info/top_level.txt
data/config/notario.cfg
ntr/__init__.py
ntr/cli/__init__.py
ntr/cli/main.py
ntr/cli/controllers/__init__.py
ntr/cli/controllers/base.py
ntr/core/__init__.py
ntr/core/exc.py
ntr/core/note.py
tests/__init__.py
tests/notario_test.py
tests/note_test.py