Metadata-Version: 1.0
Name: Notario.minion
Version: 0.6.0
Summary: A command-line utility to manage notes.
Home-page: https://github.com/goliatone/notario
Author: goliatone
Author-email: hello@goliatone.com
License: MIT
Keywords: command-line utils notes
Platform: UNKNOWN
Classifier: Development Status :: 3 - Alpha
Classifier: Environment :: Console
Classifier: Intended Audience :: Other Audience
Classifier: License :: OSI Approved :: MIT License
Classifier: Operating System :: MacOS :: MacOS X
Classifier: Operating System :: POSIX
Classifier: Programming Language :: Python
Classifier: Topic :: Utilities
